weather_ms_first/__init__.py
weather_ms_first/cli.py
weather_ms_first/server.py
weather_ms_first-0.2.0.dist-info/METADATA
weather_ms_first-0.2.0.dist-info/WHEEL
weather_ms_first-0.2.0.dist-info/entry_points.txt
weather_ms_first-0.2.0.dist-info/RECORD
