Metadata-Version: 2.4
Name: weather-ms-first
Version: 0.2.0
Summary: Add your description here
Requires-Python: >=3.10
Requires-Dist: mcp[cli]>=1.13.0
Requires-Dist: requests>=2.32.4
